setup.py
kabob/__init__.py
kabob/wand.py
kabob.egg-info/PKG-INFO
kabob.egg-info/SOURCES.txt
kabob.egg-info/dependency_links.txt
kabob.egg-info/top_level.txt