Metadata-Version: 1.1
Name: kabob
Version: 0.1.0
Summary: Skewer your objects with complex iterators
Home-page: https://github.com/bitlang/kabob
Author: Josh Junon
Author-email: josh@junon.me
License: UNKNOWN
Download-URL: https://github.com/bitlang/kabob/archive/0.1.0.tar.gz
Keywords: _,iterator,object,compose
Platform: UNKNOWN
